sphinx_related_links/__init__.py
sphinx_related_links/_version.py
sphinx_related_links/callback.py
sphinx_related_links/common.py
sphinx_related_links/_static/related-links.css
sphinx_related_links-0.1.2.dist-info/licenses/LICENSE
sphinx_related_links-0.1.2.dist-info/METADATA
sphinx_related_links-0.1.2.dist-info/WHEEL
sphinx_related_links-0.1.2.dist-info/top_level.txt
sphinx_related_links-0.1.2.dist-info/RECORD
