Metadata-Version: 2.4
Name: sphinx-related-links
Version: 0.1.2
Summary: A Sphinx extension for adding related links to documentation pages.
License-Expression: GPL-3.0
Requires-Python: >=3.10
License-File: LICENSE
Requires-Dist: docutils>=0.21.2
Requires-Dist: sphinx>=7.0
Requires-Dist: requests
Requires-Dist: beautifulsoup4
Dynamic: license-file
